contas_orama/admin.py
contas_orama/apps.py
contas_orama/models.py
contas_orama/pagination.py
contas_orama/permissions.py
contas_orama/serializers.py
contas_orama/tests.py
contas_orama/urls.py
contas_orama/views.py
contas_orama/__init__.py
contas_orama/migrations/0001_initial.py
contas_orama/migrations/__init__.py
contas_orama-0.1.0.dist-info/DESCRIPTION.rst
contas_orama-0.1.0.dist-info/METADATA
contas_orama-0.1.0.dist-info/metadata.json
contas_orama-0.1.0.dist-info/RECORD
contas_orama-0.1.0.dist-info/top_level.txt
contas_orama-0.1.0.dist-info/WHEEL
