Metadata-Version: 2.0
Name: contas-orama
Version: 0.1.0
Summary: API para gestão de contas financeiras
Home-page: https://github.com/felippemsc/teste_orama
Author: Felippe
Author-email: felippemsc@gmail.com
License: UNKNOWN
Platform: UNKNOWN
Classifier: Environment :: Web Environment
Classifier: Framework :: Django
Classifier: Intended Audience :: Developers
Classifier: Operating System :: OS Independent
Classifier: Programming Language :: Python
Classifier: Programming Language :: Python :: 3.6
Classifier: Topic :: Internet :: WWW/HTTP
Classifier: License :: OSI Approved :: MIT License
